HowtodoinjavaSpringJiaochengChuyi/README.md
HowtodoinjavaSpringJiaochengChuyi/__init__.py
HowtodoinjavaSpringJiaochengChuyi/__main__.py
HowtodoinjavaSpringJiaochengChuyi/file.epub
HowtodoinjavaSpringJiaochengChuyi/index.html
HowtodoinjavaSpringJiaochengChuyi/css/__init__.py
HowtodoinjavaSpringJiaochengChuyi/css/annotations.css
HowtodoinjavaSpringJiaochengChuyi/css/main.css
HowtodoinjavaSpringJiaochengChuyi/css/normalize.css
HowtodoinjavaSpringJiaochengChuyi/css/popup.css
HowtodoinjavaSpringJiaochengChuyi/font/__init__.py
HowtodoinjavaSpringJiaochengChuyi/font/fontello.eot
HowtodoinjavaSpringJiaochengChuyi/font/fontello.svg
HowtodoinjavaSpringJiaochengChuyi/font/fontello.ttf
HowtodoinjavaSpringJiaochengChuyi/font/fontello.woff
HowtodoinjavaSpringJiaochengChuyi/img/__init__.py
HowtodoinjavaSpringJiaochengChuyi/img/annotator-glyph-sprite.png
HowtodoinjavaSpringJiaochengChuyi/img/annotator-icon-sprite.png
HowtodoinjavaSpringJiaochengChuyi/img/apple-touch-icon.png
HowtodoinjavaSpringJiaochengChuyi/img/cancelfullscreen.png
HowtodoinjavaSpringJiaochengChuyi/img/close.png
HowtodoinjavaSpringJiaochengChuyi/img/fullscreen.png
HowtodoinjavaSpringJiaochengChuyi/img/loader.gif
HowtodoinjavaSpringJiaochengChuyi/img/menu-icon.png
HowtodoinjavaSpringJiaochengChuyi/img/save.png
HowtodoinjavaSpringJiaochengChuyi/img/saved.png
HowtodoinjavaSpringJiaochengChuyi/img/settings-s.png
HowtodoinjavaSpringJiaochengChuyi/img/settings.png
HowtodoinjavaSpringJiaochengChuyi/img/star.png
HowtodoinjavaSpringJiaochengChuyi/js/__init__.py
HowtodoinjavaSpringJiaochengChuyi/js/epub.js
HowtodoinjavaSpringJiaochengChuyi/js/epub.min.js
HowtodoinjavaSpringJiaochengChuyi/js/epub.min.map
HowtodoinjavaSpringJiaochengChuyi/js/hooks.min.js
HowtodoinjavaSpringJiaochengChuyi/js/hooks.min.map
HowtodoinjavaSpringJiaochengChuyi/js/reader.js
HowtodoinjavaSpringJiaochengChuyi/js/reader.js.map
HowtodoinjavaSpringJiaochengChuyi/js/reader.min.js
HowtodoinjavaSpringJiaochengChuyi/js/reader.min.map
howtodoinjava_spring_jiaocheng_chuyi-2024.3.5.0.dist-info/METADATA
howtodoinjava_spring_jiaocheng_chuyi-2024.3.5.0.dist-info/WHEEL
howtodoinjava_spring_jiaocheng_chuyi-2024.3.5.0.dist-info/entry_points.txt
howtodoinjava_spring_jiaocheng_chuyi-2024.3.5.0.dist-info/top_level.txt
howtodoinjava_spring_jiaocheng_chuyi-2024.3.5.0.dist-info/RECORD
